Verilog_Test/Full_Adder/full_adder.v
module full_adder (
    input wire a,
    input wire b,
    input wire cin,
    output wire sum,
    output wire cout
);
    assign sum = a ^ b ^ cin; // Sum is the XOR of a, b, and cin
    assign cout = (a & b) | (b & cin) | (a & cin); // Carry out is generated if any two inputs are high
endmodule

Verilog_Test/Full_Adder/full_adder_tb.v
module full_adder_tb;
    reg a;
    reg b;
    reg cin;

    wire sum;
    wire cout;

    full_adder uut (
        .a(a),
        .b(b),
        .cin(cin),
        .sum(sum),
        .cout(cout)
    );
initial begin 
    $dumpfile ("full_adder.vcd");
    $dumpvars(0, full_adder_tb);

    a=0; b=0; cin=0;
    #10;
    $display ("a=%b, b=%b, cin=%b, sum=%b, cout=%b", a, b, cin, sum, cout);
    a=0; b=0; cin=1;
    #10;
    $display ("a=%b, b=%b, cin=%b, sum=%b, cout=%b", a, b, cin, sum, cout);
    a=0; b=1; cin=0;
    #10;
    $display ("a=%b, b=%b, cin=%b, sum=%b, cout=%b", a, b, cin, sum, cout);
    a=0; b=1; cin=1;
    #10;
    $display ("a=%b, b=%b, cin=%b, sum=%b, cout=%b", a, b, cin, sum, cout);
    a=1; b=0; cin=0;
    #10;
    $display ("a=%b, b=%b, cin=%b, sum=%b, cout=%b", a, b, cin, sum, cout);
    a=1; b=0; cin=1;
    #10;
    $display ("a=%b, b=%b, cin=%b, sum=%b, cout=%b", a, b, cin, sum, cout);
    a=1; b=1; cin=0;
    #10;
    $display ("a=%b, b=%b, cin=%b, sum=%b, cout=%b", a, b, cin, sum, cout);
    a=1; b=1; cin=1;
    #10;
    $display ("a=%b, b=%b, cin=%b, sum=%b, cout=%b", a, b, cin, sum, cout);
    $finish;
end
endmodule

Verilog_Test/Full_Adder/full_adder.vcd
$date
	Tue Aug 11 23:25:17 2026
$end
$version
	Icarus Verilog
$end
$timescale
	1s
$end
$scope module full_adder_tb $end
$var wire 1 ! sum $end
$var wire 1 " cout $end
$var reg 1 # a $end
$var reg 1 $ b $end
$var reg 1 % cin $end
$scope module uut $end
$var wire 1 # a $end
$var wire 1 $ b $end
$var wire 1 % cin $end
$var wire 1 " cout $end
$var wire 1 ! sum $end
$upscope $end
$upscope $end
$enddefinitions $end
$comment Show the parameter values. $end
$dumpall
$end
#0
$dumpvars
0%
0$
0#
0"
0!
$end
#10
1!
1%
#20
0%
1$
#30
1"
0!
1%
#40
0"
1!
0%
0$
1#
#50
1"
0!
1%
#60
0%
1$
#70
1!
1%
