Verilog_Test/Counter/counter.v
module counter (
    input clk,
    input rst,
    output reg [3:0] count
);

    always @(posedge clk or posedge rst) begin
        if (rst) begin
            count <=4'b0000; // Reset count to 0
        end else begin
            count <= count + 1; // Increment count on each clock cycle
        end 
    end 
endmodule

Verilog_Test/Counter/counter_tb.v
module counter_tb;
    reg clk;
    reg rst;
    wire [3:0] count;

    counter uut (
        .clk(clk),
        .rst(rst),
        .count(count)
    );

always #10 clk = ~clk; // Toggle clock every 10 time units

initial begin 
    $dumpfile("counter.vcd");
    $dumpvars(0, counter_tb);
    clk=0;
    rst=1;
    #20;
    rst=0;
    #480;
    $finish;
end
endmodule

Verilog_Test/Counter/counter.vcd
$date
	Mon Aug 10 02:20:18 2026
$end
$version
	Icarus Verilog
$end
$timescale
	1s
$end
$scope module counter_tb $end
$var wire 4 ! count [3:0] $end
$var reg 1 " clk $end
$var reg 1 # rst $end
$scope module uut $end
$var wire 1 " clk $end
$var wire 1 # rst $end
$var reg 4 $ count [3:0] $end
$upscope $end
$upscope $end
$enddefinitions $end
$comment Show the parameter values. $end
$dumpall
$end
#0
$dumpvars
b0 $
1#
0"
b0 !
$end
#10
1"
#20
0"
0#
#30
b1 !
b1 $
1"
#40
0"
#50
b10 !
b10 $
1"
#60
0"
#70
b11 !
b11 $
1"
#80
0"
#90
b100 !
b100 $
1"
#100
0"
#110
b101 !
b101 $
1"
#120
0"
#130
b110 !
b110 $
1"
#140
0"
#150
b111 !
b111 $
1"
#160
0"
#170
b1000 !
b1000 $
1"
#180
0"
#190
b1001 !
b1001 $
1"
#200
0"
#210
b1010 !
b1010 $
1"
#220
0"
#230
b1011 !
b1011 $
1"
#240
0"
#250
b1100 !
b1100 $
1"
#260
0"
#270
b1101 !
b1101 $
1"
#280
0"
#290
b1110 !
b1110 $
1"
#300
0"
#310
b1111 !
b1111 $
1"
#320
0"
#330
b0 !
b0 $
1"
#340
0"
#350
b1 !
b1 $
1"
#360
0"
#370
b10 !
b10 $
1"
#380
0"
#390
b11 !
b11 $
1"
#400
0"
#410
b100 !
b100 $
1"
#420
0"
#430
b101 !
b101 $
1"
#440
0"
#450
b110 !
b110 $
1"
#460
0"
#470
b111 !
b111 $
1"
#480
0"
#490
b1000 !
b1000 $
1"
